src/demux_1x8.v
module demux_1x8(input wire i, input wire [2:0] s, output wire [7:0] o);
  // Preserve the original lab ordering: 000 -> o[7]
  assign o = i ? (8'b10000000 >> s) : 8'b0;
endmodule

sim/tb_demux_1x8.sv
`timescale 1ns/1ps
module tb_demux_1x8;
  reg i; reg [2:0] s; wire [7:0] o; demux_1x8 dut(i,s,o);
  integer n,checked=0;
  reg [7:0] expected;
  initial begin
    $dumpfile("wave.vcd"); $dumpvars(0,tb_demux_1x8);

    for(n=0;n<16;n=n+1) begin
      {i,s}=n;
      expected=(n>=8) ? (128 >> (n%8)) : 0;
      #10;
      if (o !== expected)
        $fatal(1,"FAIL demux_1x8 vector:%0d expected:%h actual:%h",n,expected,o);
      checked=checked+1;
    end
    if(checked!=16) $fatal(1,"incomplete test");
    $display("LAB1_PASS demux_1x8 cases=%0d",checked);
    $finish;
  end
  initial begin #100000; $fatal(1,"Watchdog"); end
endmodule

demux_1x8.sim/sim_1/behav/xsim/wave.vcd
$date
   Tue Sep 15 11:27:28 2026
$end

$version
  2026.1
  $dumpfile ("wave.vcd") 
$end

$timescale
  1ps
$end

$scope module tb_demux_1x8 $end
$var reg 1 ! i $end
$var reg 3 " s [2:0] $end
$var wire 8 # o [7:0] $end
$var integer 32 $ n [31:0] $end
$var integer 32 % checked [31:0] $end
$var reg 8 & expected [7:0] $end
$scope module dut $end
$var wire 1 ' i $end
$var wire 3 ( s [2:0] $end
$var wire 8 # o [7:0] $end
$upscope $end
$upscope $end
$enddefinitions $end

#0
$dumpvars
0!
b0 "
b0 #
b0 $
b0 %
b0 &
0'
b0 (
$end

#10000
b1 "
b1 $
b1 %
b1 (

#20000
b10 "
b10 $
b10 %
b10 (

#30000
b11 "
b11 $
b11 %
b11 (

#40000
b100 "
b100 $
b100 %
b100 (

#50000
b101 "
b101 $
b101 %
b101 (

#60000
b110 "
b110 $
b110 %
b110 (

#70000
b111 "
b111 $
b111 %
b111 (

#80000
1!
b0 "
b10000000 #
b1000 $
b1000 %
b10000000 &
1'
b0 (

#90000
b1 "
b1000000 #
b1001 $
b1001 %
b1000000 &
b1 (

#100000
b10 "
b100000 #
b1010 $
b1010 %
b100000 &
b10 (

#110000
b11 "
b10000 #
b1011 $
b1011 %
b10000 &
b11 (

#120000
b100 "
b1000 #
b1100 $
b1100 %
b1000 &
b100 (

#130000
b101 "
b100 #
b1101 $
b1101 %
b100 &
b101 (

#140000
b110 "
b10 #
b1110 $
b1110 %
b10 &
b110 (

#150000
b111 "
b1 #
b1111 $
b1111 %
b1 &
b111 (

#160000
b10000 $
b10000 %
